XianxingdaishuDeJiheYiyiTujieXianxingdaishu/README.md
XianxingdaishuDeJiheYiyiTujieXianxingdaishu/__init__.py
XianxingdaishuDeJiheYiyiTujieXianxingdaishu/__main__.py
XianxingdaishuDeJiheYiyiTujieXianxingdaishu/file.pdf
XianxingdaishuDeJiheYiyiTujieXianxingdaishu/index.html
xianxingdaishu_de_jihe_yiyi_tujie_xianxingdaishu-2024.3.2.0.dist-info/METADATA
xianxingdaishu_de_jihe_yiyi_tujie_xianxingdaishu-2024.3.2.0.dist-info/WHEEL
xianxingdaishu_de_jihe_yiyi_tujie_xianxingdaishu-2024.3.2.0.dist-info/entry_points.txt
xianxingdaishu_de_jihe_yiyi_tujie_xianxingdaishu-2024.3.2.0.dist-info/top_level.txt
xianxingdaishu_de_jihe_yiyi_tujie_xianxingdaishu-2024.3.2.0.dist-info/RECORD
